http_uploader/__init__.py
http_uploader/__main__.py
http_uploader/cli/__init__.py
http_uploader/cli/engine/__init__.py
http_uploader/cli/engine/common.py
http_uploader/cli/engine/dto/__init__.py
http_uploader/cli/engine/dto/args/__init__.py
http_uploader/cli/engine/dto/args/common.py
http_uploader/cli/engine/dto/response/__init__.py
http_uploader/cli/engine/dto/response/common.py
http_uploader/cli/engine/http_uploader.py
http_uploader/facade/__init__.py
http_uploader/facade/common.py
http_uploader/facade/http_uploader.py
http_uploader/facade/proxy.py
http_uploader/finder/__init__.py
http_uploader/finder/common.py
http_uploader/finder/json.py
http_uploader/http/__init__.py
http_uploader/http/common.py
http_uploader/http/dto/__init__.py
http_uploader/http/dto/client_request.py
http_uploader/http/dto/response.py
http_uploader/http/post.py
http_uploader/utils/__init__.py
http_uploader/utils/file/__init__.py
http_uploader/utils/file/common.py
http_uploader/utils/file/txt.py
http_uploader/utils/filter/__init__.py
http_uploader/utils/filter/common.py
http_uploader/utils/filter/compare.py
http_uploader/utils/filter/extented_compare.py
http_uploader/utils/parts.py
http_uploader_cli-0.1.4.dist-info/METADATA
http_uploader_cli-0.1.4.dist-info/WHEEL
http_uploader_cli-0.1.4.dist-info/RECORD
